examples/load_by_id.py
examples/load_by_year_base_profile.py
examples/load_cwe_787_remote_zero_click_in_apps_profile.py
examples/load_default_base_profile.py
examples/load_default_basic_profile.py
examples/load_single_app_profile.py
examples/load_zero_click_profile.py
nvdutils/__init__.py
nvdutils/collector.py
nvdutils/common/__init__.py
nvdutils/common/constants.py
nvdutils/common/enums/__init__.py
nvdutils/common/enums/cve.py
nvdutils/common/enums/metrics.py
nvdutils/common/enums/weaknesses.py
nvdutils/data/__init__.py
nvdutils/data/collections/__init__.py
nvdutils/data/collections/collection.py
nvdutils/data/collections/dictionaries/__init__.py
nvdutils/data/collections/dictionaries/dictionary.py
nvdutils/data/collections/dictionaries/yearly_dictionary.py
nvdutils/data/criteria/__init__.py
nvdutils/data/criteria/base.py
nvdutils/data/criteria/configurations.py
nvdutils/data/criteria/cve.py
nvdutils/data/criteria/descriptions.py
nvdutils/data/criteria/metrics.py
nvdutils/data/criteria/weaknesses.py
nvdutils/data/profiles/__init__.py
nvdutils/data/profiles/base.py
nvdutils/data/profiles/basic.py
nvdutils/data/profiles/single_app.py
nvdutils/data/profiles/zero_click.py
nvdutils/data/stats/__init__.py
nvdutils/data/stats/base.py
nvdutils/handlers/__init__.py
nvdutils/handlers/files/__init__.py
nvdutils/handlers/files/base.py
nvdutils/handlers/files/json_reader.py
nvdutils/handlers/strategies/__init__.py
nvdutils/handlers/strategies/base.py
nvdutils/handlers/strategies/by_year.py
nvdutils/handlers/strategies/default.py
nvdutils/loaders/__init__.py
nvdutils/loaders/base.py
nvdutils/loaders/json/__init__.py
nvdutils/loaders/json/default.py
nvdutils/loaders/json/yearly.py
nvdutils/models/__init__.py
nvdutils/models/cve.py
nvdutils/models/configurations/__init__.py
nvdutils/models/configurations/configuration.py
nvdutils/models/configurations/cpe_match.py
nvdutils/models/configurations/node.py
nvdutils/models/descriptions/__init__.py
nvdutils-3.5.0.dist-info/licenses/LICENSE
nvdutils-3.5.0.dist-info/METADATA
nvdutils-3.5.0.dist-info/WHEEL
nvdutils-3.5.0.dist-info/top_level.txt
nvdutils-3.5.0.dist-info/RECORD
